{
  "clips": [
    {
      "act": "Jean-Michel Jarre",
      "yt": "71DOHvfFDBY",
      "where": "13 Jul · Starlite, Marbella"
    },
    {
      "act": "Sting",
      "yt": "C3lWwBslWqg",
      "where": "13 Jul · Marenostrum, Fuengirola"
    },
    {
      "act": "Anastacia",
      "yt": "TnOy6HEf7HU",
      "where": "14 Jul · Starlite, Marbella"
    },
    {
      "act": "Juan Luis Guerra",
      "yt": "K3S96fUGrEY",
      "where": "15 Jul · Starlite, Marbella"
    },
    {
      "act": "UB40",
      "yt": "zXt56MB-3vc",
      "where": "16 Jul · Marbella Arena, Marbella"
    },
    {
      "act": "Yandel",
      "yt": "U516oP9nt2o",
      "where": "18 Jul · Starlite, Marbella"
    },
    {
      "act": "John Legend",
      "yt": "450p7goxZqg",
      "where": "20 Jul · Starlite, Marbella"
    },
    {
      "act": "Diana Krall",
      "yt": "v5FVmJKPSrY",
      "where": "21 Jul · Starlite, Marbella"
    },
    {
      "act": "Carlos Rivera",
      "yt": "Uhdnk5dgMZk",
      "where": "22 Jul · Starlite, Marbella"
    },
    {
      "act": "Kool & The Gang",
      "yt": "sLuNC5RCjY4",
      "where": "23 Jul · Starlite, Marbella"
    }
  ],
  "thumbs": {
    "Jean-Michel Jarre": "71DOHvfFDBY",
    "Anastacia": "TnOy6HEf7HU",
    "Juan Luis Guerra 4.40": "K3S96fUGrEY",
    "UB40 featuring Ali Campbell": "zXt56MB-3vc",
    "Josh Baker": "vsK1uUgrqjk",
    "Mora": "uU9Jor-8w1I",
    "Candlelight: Tribute to ABBA and More": "xFrGuyw1V8s",
    "Yandel": "U516oP9nt2o",
    "Candlelight: Queen vs. ABBA": "fJ9rUzIMcZQ",
    "Candlelight: Coldplay vs. Imagine Dragons": "dvgZkm1xWPE",
    "John Legend": "450p7goxZqg",
    "Diana Krall": "v5FVmJKPSrY",
    "Carlos Rivera": "Uhdnk5dgMZk",
    "Kool & The Gang": "sLuNC5RCjY4",
    "Miguel Ríos": "UQ_3Ba4NMIw",
    "Candlelight Open Air: The Best of Hans Zimmer in Marbella": "c56t7upa8Bk",
    "Ara Malikian": "S9fL4XSKqHI",
    "Zucchero": "IA5pBAzok3w",
    "Beret": "sK3TzV0cnVU",
    "Manuel Turizo & Mau y Ricky": "5_Y7erPV8O0",
    "Rosana": "sd6-BHgqwjk",
    "Rosario": "F1lf6kJzQWM",
    "Sergio Dalma + Sanguijuelas del Guadiana": "zlmRGWNJE3c",
    "Candlelight: Tribute to Hans Zimmer": "c56t7upa8Bk",
    "Candlelight Open Air: The Best of Hans Zimmer": "c56t7upa8Bk"
  }
}